Metadata-Version: 2.1
Name: phone-number-validator
Version: 1.0.0
Summary: Validate Phone Numbers using NumLookupAPI
Home-page: https://github.com/ashutoshkrris/phone-number-validator
License: Apache-2.0
Author: Ashutosh Krishna
Author-email: ashutoshbritish@gmail.com
Requires-Python: >=3.11,<4.0
Classifier: License :: OSI Approved :: Apache Software License
Classifier: Programming Language :: Python :: 3
Classifier: Programming Language :: Python :: 3.11
Requires-Dist: requests (>=2.28.2,<3.0.0)
Project-URL: Repository, https://github.com/ashutoshkrris/phone-number-validator
